[
    {
        "title": "静夜思",
        "author": "李白",
        "dynasty": "唐",
        "content": "窗前明月光，疑是地上霜。\n举头问明月，低头思故乡。"
    },
    {
        "title": "春晓",
        "author": "杜甫",
        "dynasty": "唐",
        "content": "春眠不觉晓，处处闻啼鸟。\n夜来风雨声，花落知多少。"
    },
    {
        "title": "画鸡",
        "author": "唐寅",
        "dynasty": "明",
        "content": "头上红冠不用裁，满身雪白走将来。\n平生不敢轻言语，一叫千门万户开。"
    },
    {
        "title": "江南",
        "author": "汉乐府",
        "dynasty": "两汉",
        "content": "江南可采莲，莲叶何田田。鱼戏莲叶间。\n鱼戏莲叶东，鱼戏莲叶西，鱼戏莲叶南，鱼戏莲叶北。"
    }
]